{
  "schema": "foxai.kayocks_study.index_receipt.v1",
  "created": "2026-07-18T23:33:18-06:00",
  "verified": true,
  "library_root": "Z:\\FOXAI\\Library",
  "database": "Z:\\FOXAI\\KAYOCKS_STUDY_BIBLIOTHECA_V1\\Data\\bibliotheca.sqlite3",
  "source_files_modified": 0,
  "source_files_deleted": 0,
  "network_used": false,
  "original_pdfs_preserved": true,
  "result": {
    "ok": true,
    "cancelled": false,
    "completed": "2026-07-18T23:33:18-06:00",
    "elapsed_seconds": 4.804,
    "pdfs_found": 97,
    "files_processed": 97,
    "indexed_or_updated": 1,
    "unchanged": 96,
    "removed_missing": 0,
    "failed": 0,
    "database_documents": 97,
    "database_pages": 11619,
    "database_text_chars": 23286420,
    "original_files_modified": 0,
    "original_files_deleted": 0
  }
}