{
  "stage": "USB C3I",
  "name": "Normal Enablement and Retention Review",
  "mode": "read_only_no_launch_fail_closed",
  "accepted_input": "C3H_FIRST_START_VERIFIED_STOPPED_READY_FOR_C3I_REVIEW",
  "writes_allowed": [
    "FOXAI_USBC3I_NORMAL_ENABLEMENT_REVIEW/REVIEW_OUTPUT/<timestamp>"
  ],
  "forbidden": [
    "ComfyUI launch",
    "FOXAI/WebUI/Desktop launch",
    "network bind or connection",
    "live launcher or source modification",
    "Runtime/ComfyUI/site-packages modification",
    "custom-node execution or enablement",
    "package installation or removal",
    "log deletion or pruning"
  ],
  "next_gate": "C3J controlled normal-enablement apply requires fresh explicit operator approval"
}
