{
  "created_at": "2026-07-21T23:36:27.664982Z",
  "entries": [
    {
      "existed": false,
      "relative_path": "System\\AgentFoxTechnicalCore\\DESKTOP_RECOVERY_HELPER_DEPENDENCY_CONTRACT_V1.json",
      "sha256": null,
      "size": null
    },
    {
      "existed": false,
      "relative_path": "System\\AgentFoxTechnicalCore\\README_V1A3C5.md",
      "sha256": null,
      "size": null
    },
    {
      "existed": false,
      "relative_path": "System\\AgentFoxTechnicalCore\\desktop_recovery_helper_dependency_closure_v1.py",
      "sha256": null,
      "size": null
    }
  ],
  "mission_id": "ENG-20260721-233008-E93FBD",
  "project_root": "Z:\\FOXAI",
  "snapshot_sha256": "dff6c5f44ab8e5e7ed012e0c23c7d94596c5b11774a3e97af72c7f60f9688214",
  "snapshot_zip": "Z:\\FOXAI\\System\\EngineeringWorkshop\\snapshots\\ENG-20260721-233008-E93FBD\\snapshot_20260721T233627661841Z.zip"
}