{
  "schema": "foxai.necroscope.rules_packets.v1",
  "built": "2026-07-18T18:22:50-06:00",
  "read_only_sources": true,
  "network_used": false,
  "source_database": "Z:\\FOXAI\\Projects\\NecroscopeCampaign\\SourceIndexV1\\necroscope_sources.sqlite3",
  "packets": {
    "agent_managed_deck_rules": {
      "title": "Agent-Managed Deck Rules Packet",
      "path": "Z:\\FOXAI\\Projects\\NecroscopeCampaign\\RulesPacketsV1\\agent_managed_deck_rules.md",
      "page_count": 9,
      "references": [
        {
          "book_key": "deadspeak_dossier",
          "title": "Deadspeak Dossier",
          "page_number": 26,
          "low_text": false
        },
        {
          "book_key": "deadspeak_dossier",
          "title": "Deadspeak Dossier",
          "page_number": 27,
          "low_text": false
        },
        {
          "book_key": "deadspeak_dossier",
          "title": "Deadspeak Dossier",
          "page_number": 28,
          "low_text": false
        },
        {
          "book_key": "e_branch_psionics",
          "title": "E-Branch Guide to Psionics",
          "page_number": 126,
          "low_text": false
        },
        {
          "book_key": "e_branch_psionics",
          "title": "E-Branch Guide to Psionics",
          "page_number": 127,
          "low_text": false
        },
        {
          "book_key": "e_branch_psionics",
          "title": "E-Branch Guide to Psionics",
          "page_number": 128,
          "low_text": true
        },
        {
          "book_key": "world_of_necroscope",
          "title": "MasterBook - World of Necroscope",
          "page_number": 7,
          "low_text": false
        },
        {
          "book_key": "world_of_necroscope",
          "title": "MasterBook - World of Necroscope",
          "page_number": 8,
          "low_text": false
        },
        {
          "book_key": "world_of_necroscope",
          "title": "MasterBook - World of Necroscope",
          "page_number": 9,
          "low_text": false
        }
      ]
    },
    "core_resolution_rules": {
      "title": "Core Resolution Rules Packet",
      "path": "Z:\\FOXAI\\Projects\\NecroscopeCampaign\\RulesPacketsV1\\core_resolution_rules.md",
      "page_count": 42,
      "references": [
        {
          "book_key": "deadspeak_dossier",
          "title": "Deadspeak Dossier",
          "page_number": 26,
          "low_text": false
        },
        {
          "book_key": "deadspeak_dossier",
          "title": "Deadspeak Dossier",
          "page_number": 27,
          "low_text": false
        },
        {
          "book_key": "deadspeak_dossier",
          "title": "Deadspeak Dossier",
          "page_number": 28,
          "low_text": false
        },
        {
          "book_key": "e_branch_psionics",
          "title": "E-Branch Guide to Psionics",
          "page_number": 13,
          "low_text": false
        },
        {
          "book_key": "e_branch_psionics",
          "title": "E-Branch Guide to Psionics",
          "page_number": 14,
          "low_text": false
        },
        {
          "book_key": "e_branch_psionics",
          "title": "E-Branch Guide to Psionics",
          "page_number": 15,
          "low_text": false
        },
        {
          "book_key": "e_branch_psionics",
          "title": "E-Branch Guide to Psionics",
          "page_number": 16,
          "low_text": false
        },
        {
          "book_key": "e_branch_psionics",
          "title": "E-Branch Guide to Psionics",
          "page_number": 17,
          "low_text": false
        },
        {
          "book_key": "e_branch_psionics",
          "title": "E-Branch Guide to Psionics",
          "page_number": 19,
          "low_text": true
        },
        {
          "book_key": "e_branch_psionics",
          "title": "E-Branch Guide to Psionics",
          "page_number": 20,
          "low_text": false
        },
        {
          "book_key": "e_branch_psionics",
          "title": "E-Branch Guide to Psionics",
          "page_number": 21,
          "low_text": false
        },
        {
          "book_key": "e_branch_psionics",
          "title": "E-Branch Guide to Psionics",
          "page_number": 22,
          "low_text": false
        },
        {
          "book_key": "e_branch_psionics",
          "title": "E-Branch Guide to Psionics",
          "page_number": 23,
          "low_text": false
        },
        {
          "book_key": "e_branch_psionics",
          "title": "E-Branch Guide to Psionics",
          "page_number": 24,
          "low_text": false
        },
        {
          "book_key": "e_branch_psionics",
          "title": "E-Branch Guide to Psionics",
          "page_number": 27,
          "low_text": false
        },
        {
          "book_key": "e_branch_psionics",
          "title": "E-Branch Guide to Psionics",
          "page_number": 28,
          "low_text": false
        },
        {
          "book_key": "e_branch_psionics",
          "title": "E-Branch Guide to Psionics",
          "page_number": 29,
          "low_text": false
        },
        {
          "book_key": "e_branch_psionics",
          "title": "E-Branch Guide to Psionics",
          "page_number": 30,
          "low_text": false
        },
        {
          "book_key": "wamphyri",
          "title": "Wamphyri",
          "page_number": 21,
          "low_text": false
        },
        {
          "book_key": "wamphyri",
          "title": "Wamphyri",
          "page_number": 22,
          "low_text": false
        },
        {
          "book_key": "wamphyri",
          "title": "Wamphyri",
          "page_number": 23,
          "low_text": false
        },
        {
          "book_key": "world_of_necroscope",
          "title": "MasterBook - World of Necroscope",
          "page_number": 7,
          "low_text": false
        },
        {
          "book_key": "world_of_necroscope",
          "title": "MasterBook - World of Necroscope",
          "page_number": 8,
          "low_text": false
        },
        {
          "book_key": "world_of_necroscope",
          "title": "MasterBook - World of Necroscope",
          "page_number": 9,
          "low_text": false
        },
        {
          "book_key": "world_of_necroscope",
          "title": "MasterBook - World of Necroscope",
          "page_number": 24,
          "low_text": true
        },
        {
          "book_key": "world_of_necroscope",
          "title": "MasterBook - World of Necroscope",
          "page_number": 25,
          "low_text": false
        },
        {
          "book_key": "world_of_necroscope",
          "title": "MasterBook - World of Necroscope",
          "page_number": 26,
          "low_text": false
        },
        {
          "book_key": "world_of_necroscope",
          "title": "MasterBook - World of Necroscope",
          "page_number": 27,
          "low_text": false
        },
        {
          "book_key": "world_of_necroscope",
          "title": "MasterBook - World of Necroscope",
          "page_number": 28,
          "low_text": false
        },
        {
          "book_key": "world_of_necroscope",
          "title": "MasterBook - World of Necroscope",
          "page_number": 30,
          "low_text": false
        },
        {
          "book_key": "world_of_necroscope",
          "title": "MasterBook - World of Necroscope",
          "page_number": 31,
          "low_text": false
        },
        {
          "book_key": "world_of_necroscope",
          "title": "MasterBook - World of Necroscope",
          "page_number": 32,
          "low_text": false
        },
        {
          "book_key": "world_of_necroscope",
          "title": "MasterBook - World of Necroscope",
          "page_number": 33,
          "low_text": false
        },
        {
          "book_key": "world_of_necroscope",
          "title": "MasterBook - World of Necroscope",
          "page_number": 34,
          "low_text": false
        },
        {
          "book_key": "world_of_necroscope",
          "title": "MasterBook - World of Necroscope",
          "page_number": 35,
          "low_text": false
        },
        {
          "book_key": "world_of_necroscope",
          "title": "MasterBook - World of Necroscope",
          "page_number": 36,
          "low_text": false
        },
        {
          "book_key": "world_of_necroscope",
          "title": "MasterBook - World of Necroscope",
          "page_number": 37,
          "low_text": false
        },
        {
          "book_key": "world_of_necroscope",
          "title": "MasterBook - World of Necroscope",
          "page_number": 38,
          "low_text": false
        },
        {
          "book_key": "world_of_necroscope",
          "title": "MasterBook - World of Necroscope",
          "page_number": 39,
          "low_text": false
        },
        {
          "book_key": "world_of_necroscope",
          "title": "MasterBook - World of Necroscope",
          "page_number": 40,
          "low_text": false
        },
        {
          "book_key": "world_of_necroscope",
          "title": "MasterBook - World of Necroscope",
          "page_number": 42,
          "low_text": false
        },
        {
          "book_key": "world_of_necroscope",
          "title": "MasterBook - World of Necroscope",
          "page_number": 43,
          "low_text": false
        }
      ]
    },
    "character_creation_rules": {
      "title": "Character Creation Rules Packet",
      "path": "Z:\\FOXAI\\Projects\\NecroscopeCampaign\\RulesPacketsV1\\character_creation_rules.md",
      "page_count": 44,
      "references": [
        {
          "book_key": "e_branch_psionics",
          "title": "E-Branch Guide to Psionics",
          "page_number": 50,
          "low_text": false
        },
        {
          "book_key": "e_branch_psionics",
          "title": "E-Branch Guide to Psionics",
          "page_number": 73,
          "low_text": false
        },
        {
          "book_key": "e_branch_psionics",
          "title": "E-Branch Guide to Psionics",
          "page_number": 112,
          "low_text": false
        },
        {
          "book_key": "e_branch_psionics",
          "title": "E-Branch Guide to Psionics",
          "page_number": 113,
          "low_text": false
        },
        {
          "book_key": "e_branch_psionics",
          "title": "E-Branch Guide to Psionics",
          "page_number": 114,
          "low_text": false
        },
        {
          "book_key": "e_branch_psionics",
          "title": "E-Branch Guide to Psionics",
          "page_number": 115,
          "low_text": false
        },
        {
          "book_key": "e_branch_psionics",
          "title": "E-Branch Guide to Psionics",
          "page_number": 116,
          "low_text": false
        },
        {
          "book_key": "e_branch_psionics",
          "title": "E-Branch Guide to Psionics",
          "page_number": 117,
          "low_text": false
        },
        {
          "book_key": "e_branch_psionics",
          "title": "E-Branch Guide to Psionics",
          "page_number": 118,
          "low_text": false
        },
        {
          "book_key": "e_branch_psionics",
          "title": "E-Branch Guide to Psionics",
          "page_number": 119,
          "low_text": false
        },
        {
          "book_key": "e_branch_psionics",
          "title": "E-Branch Guide to Psionics",
          "page_number": 120,
          "low_text": false
        },
        {
          "book_key": "e_branch_psionics",
          "title": "E-Branch Guide to Psionics",
          "page_number": 121,
          "low_text": false
        },
        {
          "book_key": "e_branch_psionics",
          "title": "E-Branch Guide to Psionics",
          "page_number": 122,
          "low_text": false
        },
        {
          "book_key": "e_branch_psionics",
          "title": "E-Branch Guide to Psionics",
          "page_number": 125,
          "low_text": false
        },
        {
          "book_key": "e_branch_psionics",
          "title": "E-Branch Guide to Psionics",
          "page_number": 126,
          "low_text": false
        },
        {
          "book_key": "operation_nightside",
          "title": "Operation Nightside",
          "page_number": 124,
          "low_text": false
        },
        {
          "book_key": "wamphyri",
          "title": "Wamphyri",
          "page_number": 84,
          "low_text": false
        },
        {
          "book_key": "wamphyri",
          "title": "Wamphyri",
          "page_number": 92,
          "low_text": false
        },
        {
          "book_key": "world_of_necroscope",
          "title": "MasterBook - World of Necroscope",
          "page_number": 5,
          "low_text": false
        },
        {
          "book_key": "world_of_necroscope",
          "title": "MasterBook - World of Necroscope",
          "page_number": 13,
          "low_text": false
        },
        {
          "book_key": "world_of_necroscope",
          "title": "MasterBook - World of Necroscope",
          "page_number": 14,
          "low_text": false
        },
        {
          "book_key": "world_of_necroscope",
          "title": "MasterBook - World of Necroscope",
          "page_number": 16,
          "low_text": false
        },
        {
          "book_key": "world_of_necroscope",
          "title": "MasterBook - World of Necroscope",
          "page_number": 18,
          "low_text": false
        },
        {
          "book_key": "world_of_necroscope",
          "title": "MasterBook - World of Necroscope",
          "page_number": 20,
          "low_text": false
        },
        {
          "book_key": "world_of_necroscope",
          "title": "MasterBook - World of Necroscope",
          "page_number": 21,
          "low_text": false
        },
        {
          "book_key": "world_of_necroscope",
          "title": "MasterBook - World of Necroscope",
          "page_number": 22,
          "low_text": false
        },
        {
          "book_key": "world_of_necroscope",
          "title": "MasterBook - World of Necroscope",
          "page_number": 25,
          "low_text": false
        },
        {
          "book_key": "world_of_necroscope",
          "title": "MasterBook - World of Necroscope",
          "page_number": 27,
          "low_text": false
        },
        {
          "book_key": "world_of_necroscope",
          "title": "MasterBook - World of Necroscope",
          "page_number": 31,
          "low_text": false
        },
        {
          "book_key": "world_of_necroscope",
          "title": "MasterBook - World of Necroscope",
          "page_number": 32,
          "low_text": false
        },
        {
          "book_key": "world_of_necroscope",
          "title": "MasterBook - World of Necroscope",
          "page_number": 34,
          "low_text": false
        },
        {
          "book_key": "world_of_necroscope",
          "title": "MasterBook - World of Necroscope",
          "page_number": 38,
          "low_text": false
        },
        {
          "book_key": "world_of_necroscope",
          "title": "MasterBook - World of Necroscope",
          "page_number": 40,
          "low_text": false
        },
        {
          "book_key": "world_of_necroscope",
          "title": "MasterBook - World of Necroscope",
          "page_number": 43,
          "low_text": false
        },
        {
          "book_key": "world_of_necroscope",
          "title": "MasterBook - World of Necroscope",
          "page_number": 54,
          "low_text": false
        },
        {
          "book_key": "world_of_necroscope",
          "title": "MasterBook - World of Necroscope",
          "page_number": 56,
          "low_text": false
        },
        {
          "book_key": "world_of_necroscope",
          "title": "MasterBook - World of Necroscope",
          "page_number": 66,
          "low_text": false
        },
        {
          "book_key": "world_of_necroscope",
          "title": "MasterBook - World of Necroscope",
          "page_number": 72,
          "low_text": false
        },
        {
          "book_key": "world_of_necroscope",
          "title": "MasterBook - World of Necroscope",
          "page_number": 88,
          "low_text": false
        },
        {
          "book_key": "world_of_necroscope",
          "title": "MasterBook - World of Necroscope",
          "page_number": 89,
          "low_text": false
        },
        {
          "book_key": "world_of_necroscope",
          "title": "MasterBook - World of Necroscope",
          "page_number": 90,
          "low_text": false
        },
        {
          "book_key": "world_of_necroscope",
          "title": "MasterBook - World of Necroscope",
          "page_number": 93,
          "low_text": false
        },
        {
          "book_key": "world_of_necroscope",
          "title": "MasterBook - World of Necroscope",
          "page_number": 111,
          "low_text": false
        },
        {
          "book_key": "world_of_necroscope",
          "title": "MasterBook - World of Necroscope",
          "page_number": 114,
          "low_text": false
        }
      ]
    },
    "campaign_lore_seed": {
      "title": "Necroscope Campaign Lore Seed",
      "path": "Z:\\FOXAI\\Projects\\NecroscopeCampaign\\RulesPacketsV1\\campaign_lore_seed.md",
      "page_count": 36,
      "references": [
        {
          "book_key": "deadspeak_dossier",
          "title": "Deadspeak Dossier",
          "page_number": 4,
          "low_text": false
        },
        {
          "book_key": "deadspeak_dossier",
          "title": "Deadspeak Dossier",
          "page_number": 5,
          "low_text": false
        },
        {
          "book_key": "deadspeak_dossier",
          "title": "Deadspeak Dossier",
          "page_number": 6,
          "low_text": false
        },
        {
          "book_key": "deadspeak_dossier",
          "title": "Deadspeak Dossier",
          "page_number": 8,
          "low_text": false
        },
        {
          "book_key": "e_branch_psionics",
          "title": "E-Branch Guide to Psionics",
          "page_number": 4,
          "low_text": false
        },
        {
          "book_key": "e_branch_psionics",
          "title": "E-Branch Guide to Psionics",
          "page_number": 5,
          "low_text": false
        },
        {
          "book_key": "e_branch_psionics",
          "title": "E-Branch Guide to Psionics",
          "page_number": 18,
          "low_text": false
        },
        {
          "book_key": "wamphyri",
          "title": "Wamphyri",
          "page_number": 4,
          "low_text": false
        },
        {
          "book_key": "wamphyri",
          "title": "Wamphyri",
          "page_number": 5,
          "low_text": false
        },
        {
          "book_key": "world_of_necroscope",
          "title": "MasterBook - World of Necroscope",
          "page_number": 2,
          "low_text": false
        },
        {
          "book_key": "world_of_necroscope",
          "title": "MasterBook - World of Necroscope",
          "page_number": 4,
          "low_text": false
        },
        {
          "book_key": "world_of_necroscope",
          "title": "MasterBook - World of Necroscope",
          "page_number": 5,
          "low_text": false
        },
        {
          "book_key": "world_of_necroscope",
          "title": "MasterBook - World of Necroscope",
          "page_number": 6,
          "low_text": false
        },
        {
          "book_key": "world_of_necroscope",
          "title": "MasterBook - World of Necroscope",
          "page_number": 7,
          "low_text": false
        },
        {
          "book_key": "world_of_necroscope",
          "title": "MasterBook - World of Necroscope",
          "page_number": 8,
          "low_text": false
        },
        {
          "book_key": "world_of_necroscope",
          "title": "MasterBook - World of Necroscope",
          "page_number": 9,
          "low_text": false
        },
        {
          "book_key": "world_of_necroscope",
          "title": "MasterBook - World of Necroscope",
          "page_number": 11,
          "low_text": false
        },
        {
          "book_key": "world_of_necroscope",
          "title": "MasterBook - World of Necroscope",
          "page_number": 12,
          "low_text": false
        },
        {
          "book_key": "world_of_necroscope",
          "title": "MasterBook - World of Necroscope",
          "page_number": 14,
          "low_text": false
        },
        {
          "book_key": "world_of_necroscope",
          "title": "MasterBook - World of Necroscope",
          "page_number": 15,
          "low_text": false
        },
        {
          "book_key": "world_of_necroscope",
          "title": "MasterBook - World of Necroscope",
          "page_number": 16,
          "low_text": false
        },
        {
          "book_key": "world_of_necroscope",
          "title": "MasterBook - World of Necroscope",
          "page_number": 18,
          "low_text": false
        },
        {
          "book_key": "world_of_necroscope",
          "title": "MasterBook - World of Necroscope",
          "page_number": 25,
          "low_text": false
        },
        {
          "book_key": "world_of_necroscope",
          "title": "MasterBook - World of Necroscope",
          "page_number": 28,
          "low_text": false
        },
        {
          "book_key": "world_of_necroscope",
          "title": "MasterBook - World of Necroscope",
          "page_number": 29,
          "low_text": false
        },
        {
          "book_key": "world_of_necroscope",
          "title": "MasterBook - World of Necroscope",
          "page_number": 30,
          "low_text": false
        },
        {
          "book_key": "world_of_necroscope",
          "title": "MasterBook - World of Necroscope",
          "page_number": 37,
          "low_text": false
        },
        {
          "book_key": "world_of_necroscope",
          "title": "MasterBook - World of Necroscope",
          "page_number": 40,
          "low_text": false
        },
        {
          "book_key": "world_of_necroscope",
          "title": "MasterBook - World of Necroscope",
          "page_number": 43,
          "low_text": false
        },
        {
          "book_key": "world_of_necroscope",
          "title": "MasterBook - World of Necroscope",
          "page_number": 48,
          "low_text": false
        },
        {
          "book_key": "world_of_necroscope",
          "title": "MasterBook - World of Necroscope",
          "page_number": 53,
          "low_text": false
        },
        {
          "book_key": "world_of_necroscope",
          "title": "MasterBook - World of Necroscope",
          "page_number": 54,
          "low_text": false
        },
        {
          "book_key": "world_of_necroscope",
          "title": "MasterBook - World of Necroscope",
          "page_number": 58,
          "low_text": false
        },
        {
          "book_key": "world_of_necroscope",
          "title": "MasterBook - World of Necroscope",
          "page_number": 60,
          "low_text": false
        },
        {
          "book_key": "world_of_necroscope",
          "title": "MasterBook - World of Necroscope",
          "page_number": 61,
          "low_text": false
        },
        {
          "book_key": "world_of_necroscope",
          "title": "MasterBook - World of Necroscope",
          "page_number": 67,
          "low_text": false
        }
      ]
    }
  }
}