{
  "verified": true,
  "no_launch": true,
  "network_access": false,
  "process_launch": false,
  "server_bind": false,
  "root": "Z:\\FOXAI",
  "target": "Z:\\FOXAI\\Runtime\\ComfyUI\\site-packages",
  "comfy": "Z:\\FOXAI\\ComfyUI",
  "python": "Z:\\FOXAI\\Runtime\\Desktop\\python\\python.exe",
  "version": [
    3,
    14,
    6
  ],
  "isolated_flag": 1,
  "no_site_flag": 1,
  "dont_write_bytecode": true,
  "issues": [],
  "sys_path_before_activation": [
    "Z:\\FOXAI\\Runtime\\Desktop\\python\\python314.zip",
    "Z:\\FOXAI\\Runtime\\Desktop\\python\\DLLs",
    "Z:\\FOXAI\\Runtime\\Desktop\\python\\Lib",
    "Z:\\FOXAI\\Runtime\\Desktop\\python"
  ],
  "sys_path_after_activation": [
    "Z:\\FOXAI\\ComfyUI",
    "Z:\\FOXAI\\Runtime\\Desktop\\python\\python314.zip",
    "Z:\\FOXAI\\Runtime\\Desktop\\python\\DLLs",
    "Z:\\FOXAI\\Runtime\\Desktop\\python\\Lib",
    "Z:\\FOXAI\\Runtime\\Desktop\\python",
    "Z:\\FOXAI\\Runtime\\ComfyUI\\site-packages"
  ],
  "forbidden_sys_path_entries": [],
  "source_compile": {
    "verified": true,
    "compiled_file_count": 680,
    "source_tree_sha256": "f31d55dcd806ae8c487796fcb63d192b04093743897028dc96e023e207a7d98c",
    "failures": []
  },
  "imports": [
    {
      "module": "aiohttp",
      "verified": true,
      "locations": [
        "Z:\\FOXAI\\Runtime\\ComfyUI\\site-packages\\aiohttp",
        "Z:\\FOXAI\\Runtime\\ComfyUI\\site-packages\\aiohttp\\__init__.py"
      ],
      "version": "3.14.1"
    },
    {
      "module": "av",
      "verified": true,
      "locations": [
        "Z:\\FOXAI\\Runtime\\ComfyUI\\site-packages\\av",
        "Z:\\FOXAI\\Runtime\\ComfyUI\\site-packages\\av\\__init__.py"
      ],
      "version": "18.0.0"
    },
    {
      "module": "blake3",
      "verified": true,
      "locations": [
        "Z:\\FOXAI\\Runtime\\ComfyUI\\site-packages\\blake3",
        "Z:\\FOXAI\\Runtime\\ComfyUI\\site-packages\\blake3\\__init__.py"
      ],
      "version": "1.0.9"
    },
    {
      "module": "cryptography",
      "verified": true,
      "locations": [
        "Z:\\FOXAI\\Runtime\\ComfyUI\\site-packages\\cryptography",
        "Z:\\FOXAI\\Runtime\\ComfyUI\\site-packages\\cryptography\\__init__.py"
      ],
      "version": "49.0.0"
    },
    {
      "module": "huggingface_hub",
      "verified": true,
      "locations": [
        "Z:\\FOXAI\\Runtime\\ComfyUI\\site-packages\\huggingface_hub",
        "Z:\\FOXAI\\Runtime\\ComfyUI\\site-packages\\huggingface_hub\\__init__.py"
      ],
      "version": "1.21.0"
    },
    {
      "module": "kornia",
      "verified": true,
      "locations": [
        "Z:\\FOXAI\\Runtime\\ComfyUI\\site-packages\\kornia",
        "Z:\\FOXAI\\Runtime\\ComfyUI\\site-packages\\kornia\\__init__.py"
      ],
      "version": "0.8.3"
    },
    {
      "module": "numpy",
      "verified": true,
      "locations": [
        "Z:\\FOXAI\\Runtime\\ComfyUI\\site-packages\\numpy",
        "Z:\\FOXAI\\Runtime\\ComfyUI\\site-packages\\numpy\\__init__.py"
      ],
      "version": "2.5.0"
    },
    {
      "module": "OpenGL",
      "verified": true,
      "locations": [
        "Z:\\FOXAI\\Runtime\\ComfyUI\\site-packages\\OpenGL",
        "Z:\\FOXAI\\Runtime\\ComfyUI\\site-packages\\OpenGL\\__init__.py"
      ],
      "version": "3.1.10"
    },
    {
      "module": "OpenGL.GL",
      "verified": true,
      "locations": [
        "Z:\\FOXAI\\Runtime\\ComfyUI\\site-packages\\OpenGL\\GL",
        "Z:\\FOXAI\\Runtime\\ComfyUI\\site-packages\\OpenGL\\GL\\__init__.py"
      ],
      "version": ""
    },
    {
      "module": "PIL",
      "verified": true,
      "locations": [
        "Z:\\FOXAI\\Runtime\\ComfyUI\\site-packages\\PIL",
        "Z:\\FOXAI\\Runtime\\ComfyUI\\site-packages\\PIL\\__init__.py"
      ],
      "version": "12.3.0"
    },
    {
      "module": "psutil",
      "verified": true,
      "locations": [
        "Z:\\FOXAI\\Runtime\\ComfyUI\\site-packages\\psutil",
        "Z:\\FOXAI\\Runtime\\ComfyUI\\site-packages\\psutil\\__init__.py"
      ],
      "version": "7.2.2"
    },
    {
      "module": "safetensors",
      "verified": true,
      "locations": [
        "Z:\\FOXAI\\Runtime\\ComfyUI\\site-packages\\safetensors",
        "Z:\\FOXAI\\Runtime\\ComfyUI\\site-packages\\safetensors\\__init__.py"
      ],
      "version": "0.8.0"
    },
    {
      "module": "scipy",
      "verified": true,
      "locations": [
        "Z:\\FOXAI\\Runtime\\ComfyUI\\site-packages\\scipy",
        "Z:\\FOXAI\\Runtime\\ComfyUI\\site-packages\\scipy\\__init__.py"
      ],
      "version": "1.18.0"
    },
    {
      "module": "sentencepiece",
      "verified": true,
      "locations": [
        "Z:\\FOXAI\\Runtime\\ComfyUI\\site-packages\\sentencepiece",
        "Z:\\FOXAI\\Runtime\\ComfyUI\\site-packages\\sentencepiece\\__init__.py"
      ],
      "version": "0.2.1"
    },
    {
      "module": "sqlalchemy",
      "verified": true,
      "locations": [
        "Z:\\FOXAI\\Runtime\\ComfyUI\\site-packages\\sqlalchemy",
        "Z:\\FOXAI\\Runtime\\ComfyUI\\site-packages\\sqlalchemy\\__init__.py"
      ],
      "version": "2.0.51"
    },
    {
      "module": "tokenizers",
      "verified": true,
      "locations": [
        "Z:\\FOXAI\\Runtime\\ComfyUI\\site-packages\\tokenizers",
        "Z:\\FOXAI\\Runtime\\ComfyUI\\site-packages\\tokenizers\\__init__.py"
      ],
      "version": "0.22.2"
    },
    {
      "module": "torch",
      "verified": true,
      "locations": [
        "Z:\\FOXAI\\Runtime\\ComfyUI\\site-packages\\torch",
        "Z:\\FOXAI\\Runtime\\ComfyUI\\site-packages\\torch\\__init__.py"
      ],
      "version": "2.12.1+cpu"
    },
    {
      "module": "torchaudio",
      "verified": true,
      "locations": [
        "Z:\\FOXAI\\Runtime\\ComfyUI\\site-packages\\torchaudio",
        "Z:\\FOXAI\\Runtime\\ComfyUI\\site-packages\\torchaudio\\__init__.py"
      ],
      "version": "2.11.0+cpu"
    },
    {
      "module": "torchvision",
      "verified": true,
      "locations": [
        "Z:\\FOXAI\\Runtime\\ComfyUI\\site-packages\\torchvision",
        "Z:\\FOXAI\\Runtime\\ComfyUI\\site-packages\\torchvision\\__init__.py"
      ],
      "version": "0.27.1+cpu"
    },
    {
      "module": "transformers",
      "verified": true,
      "locations": [
        "Z:\\FOXAI\\Runtime\\ComfyUI\\site-packages\\transformers",
        "Z:\\FOXAI\\Runtime\\ComfyUI\\site-packages\\transformers\\__init__.py"
      ],
      "version": "5.12.1"
    },
    {
      "module": "yaml",
      "verified": true,
      "locations": [
        "Z:\\FOXAI\\Runtime\\ComfyUI\\site-packages\\yaml",
        "Z:\\FOXAI\\Runtime\\ComfyUI\\site-packages\\yaml\\__init__.py"
      ],
      "version": "6.0.3"
    },
    {
      "module": "comfy.options",
      "verified": true,
      "locations": [
        "Z:\\FOXAI\\ComfyUI\\comfy\\options.py"
      ],
      "version": ""
    },
    {
      "module": "comfy.cli_args",
      "verified": true,
      "locations": [
        "Z:\\FOXAI\\ComfyUI\\comfy\\cli_args.py"
      ],
      "version": ""
    },
    {
      "module": "folder_paths",
      "verified": true,
      "locations": [
        "Z:\\FOXAI\\ComfyUI\\folder_paths.py"
      ],
      "version": ""
    },
    {
      "module": "comfy.utils",
      "verified": true,
      "locations": [
        "Z:\\FOXAI\\ComfyUI\\comfy\\utils.py"
      ],
      "version": ""
    },
    {
      "module": "comfy.model_management",
      "verified": true,
      "locations": [
        "Z:\\FOXAI\\ComfyUI\\comfy\\model_management.py"
      ],
      "version": ""
    },
    {
      "module": "comfy.model_detection",
      "verified": true,
      "locations": [
        "Z:\\FOXAI\\ComfyUI\\comfy\\model_detection.py"
      ],
      "version": ""
    },
    {
      "module": "comfy.sd",
      "verified": true,
      "locations": [
        "Z:\\FOXAI\\ComfyUI\\comfy\\sd.py"
      ],
      "version": ""
    },
    {
      "module": "comfy.samplers",
      "verified": true,
      "locations": [
        "Z:\\FOXAI\\ComfyUI\\comfy\\samplers.py"
      ],
      "version": ""
    },
    {
      "module": "comfy_execution.graph",
      "verified": true,
      "locations": [
        "Z:\\FOXAI\\ComfyUI\\comfy_execution\\graph.py"
      ],
      "version": ""
    },
    {
      "module": "comfy_api.feature_flags",
      "verified": true,
      "locations": [
        "Z:\\FOXAI\\ComfyUI\\comfy_api\\feature_flags.py"
      ],
      "version": ""
    },
    {
      "module": "app.logger",
      "verified": true,
      "locations": [
        "Z:\\FOXAI\\ComfyUI\\app\\logger.py"
      ],
      "version": ""
    }
  ],
  "torch_cpu_test": {
    "verified": true,
    "torch_version": "2.12.1+cpu",
    "cuda_available": false,
    "result": [
      [
        4.0
      ],
      [
        10.0
      ]
    ]
  },
  "torchvision_compiled_op_test": {
    "verified": true,
    "version": "0.27.1+cpu",
    "nms_result": [
      0
    ]
  },
  "torchaudio_test": {
    "verified": true,
    "version": "2.11.0+cpu",
    "output_shape": [
      1,
      8
    ]
  },
  "comfy_cli_test": {
    "verified": true,
    "cpu": true,
    "disable_all_custom_nodes": true,
    "initializer_called": true,
    "argv": [
      "Z:\\FOXAI\\ComfyUI\\main.py",
      "--cpu",
      "--disable-all-custom-nodes",
      "--dont-print-server"
    ]
  },
  "main_py": {
    "path": "Z:\\FOXAI\\ComfyUI\\main.py",
    "size_bytes": 24428,
    "sha256": "d2580be49e7abb3218b1e7056844b2c72a2e7d8711268849429ad3b418c38bc9",
    "compiled": true,
    "executed": false
  },
  "blocked_audit_events": []
}