{
  "schema": "foxai.kayocks_study.v2b_1.plan_build_receipt.v1",
  "mission_id": "ENG-20260720-151845-F16893",
  "result": "exact_plan_built_simulated_and_fixture_verified",
  "plan_sha256": "77f2cb7f0e10879b5f76b1b0d68ef329dec72f7e22f83d83bd89f8a299a5535d",
  "changed_path_count": 2,
  "changed_paths": [
    "KAYOCKS_STUDY_BIBLIOTHECA_V1/study_server.py",
    "KAYOCKS_STUDY_BIBLIOTHECA_V1/VERIFY_KAYOCKS_STUDY_V2B_1.py"
  ],
  "validation_count": 4,
  "before_hashes": {
    "KAYOCKS_STUDY_BIBLIOTHECA_V1/study_server.py": "ae6f11a000bc8bb95343662be3358083c8e8436aac0a026891f500026e97e51d",
    "KAYOCKS_STUDY_BIBLIOTHECA_V1/VERIFY_KAYOCKS_STUDY_V2B_1.py": null
  },
  "after_hashes": {
    "KAYOCKS_STUDY_BIBLIOTHECA_V1/study_server.py": "9d7eb30f361b337bcaacf4761cb41e379f736242db2ec6579641611d966315c8",
    "KAYOCKS_STUDY_BIBLIOTHECA_V1/VERIFY_KAYOCKS_STUDY_V2B_1.py": "b6fdf958dcd4b2cd2d45c3e3f79a84d61a7358757000261f35af929c527e8e38"
  },
  "features_verified": {
    "v2a_1_tiled_home_preserved": true,
    "separate_epub_sidecar_database": true,
    "bibliotheca_pdf_schema_unchanged": true,
    "valid_epub_with_embedded_cover": true,
    "valid_epub_without_cover": true,
    "browser_placeholder_cover": true,
    "malformed_epub_needs_review": true,
    "encryption_marker_refused": true,
    "mobi_reported_unsupported": true,
    "duplicate_rescan_incremental": true,
    "missing_file_catalog_cleanup": true,
    "fiction_shelf_classification": true,
    "star_trek_collection_classification": true,
    "home_scan_action": true,
    "epub_api_http_200": true,
    "cover_api_http_200": true,
    "existing_pdf_documents_api_preserved": true,
    "existing_pdf_search_json_preserved": true,
    "original_ebook_hashes_preserved": true,
    "external_library_not_scanned": true
  },
  "tests": {
    "workshop_plan_schema_and_before_hash": "passed",
    "workshop_preview": "passed — 2 changed paths",
    "workshop_simulated_apply": "passed — 2 files",
    "source_compilation_without_bytecode": "passed",
    "embedded_javascript_syntax": "passed with node --check",
    "v2b_1_fixture_and_loopback_http_verifier": {
      "schema": "foxai.kayocks_study.v2b_1.verification.v1",
      "mission": "Kayock's Study V2B.1 — Native EPUB Discovery and Starfleet Archive Catalog",
      "result": "verified",
      "check_count": 46,
      "checks": [
        {
          "id": "main_foxai_lifecycle_present",
          "ok": true,
          "detail": ""
        },
        {
          "id": "controlled_research_desk_preserved",
          "ok": true,
          "detail": ""
        },
        {
          "id": "v1_6_verifier_preserved",
          "ok": true,
          "detail": ""
        },
        {
          "id": "v1_2_verifier_preserved",
          "ok": true,
          "detail": ""
        },
        {
          "id": "v1_2_1_verifier_preserved",
          "ok": true,
          "detail": ""
        },
        {
          "id": "v1_2_2_verifier_preserved",
          "ok": true,
          "detail": ""
        },
        {
          "id": "v2a_1_verifier_preserved",
          "ok": true,
          "detail": ""
        },
        {
          "id": "epub_catalog_backend_present",
          "ok": true,
          "detail": ""
        },
        {
          "id": "separate_sidecar_database",
          "ok": true,
          "detail": ""
        },
        {
          "id": "supported_formats_are_bounded",
          "ok": true,
          "detail": ""
        },
        {
          "id": "no_external_star_trek_scan",
          "ok": true,
          "detail": ""
        },
        {
          "id": "no_reader_or_read_aloud_yet",
          "ok": true,
          "detail": ""
        },
        {
          "id": "v2b_1_ui_present",
          "ok": true,
          "detail": ""
        },
        {
          "id": "v2a_1_tiled_home_preserved",
          "ok": true,
          "detail": ""
        },
        {
          "id": "home_scan_button_present",
          "ok": true,
          "detail": ""
        },
        {
          "id": "real_and_placeholder_covers_supported",
          "ok": true,
          "detail": ""
        },
        {
          "id": "epub_detail_is_catalog_only",
          "ok": true,
          "detail": ""
        },
        {
          "id": "html_constant_extractable",
          "ok": true,
          "detail": ""
        },
        {
          "id": "single_script_block",
          "ok": true,
          "detail": ""
        },
        {
          "id": "first_scan_completed",
          "ok": true,
          "detail": {
            "ok": true,
            "cancelled": false,
            "completed": "2026-07-20T15:34:31+00:00",
            "elapsed_seconds": 0.016,
            "pdfs_found": 1,
            "files_processed": 6,
            "indexed_or_updated": 1,
            "unchanged": 0,
            "removed_missing": 0,
            "failed": 0,
            "database_documents": 1,
            "database_pages": 1,
            "database_text_chars": 0,
            "original_files_modified": 0,
            "original_files_deleted": 0,
            "ebooks_found": 5,
            "epubs_ready": 2,
            "ebooks_needing_review": 3,
            "ebooks_indexed_or_updated": 5,
            "ebooks_unchanged": 0,
            "ebooks_removed_missing": 0,
            "ebooks_failed": 0,
            "receipt": "/tmp/kayocks_study_v2b_1_http_ifnz6ev9/Reports/20260720T153431_bibliotheca_index_receipt.json"
          }
        },
        {
          "id": "pdf_api_inventory_preserved",
          "ok": true,
          "detail": {
            "ok": true,
            "cancelled": false,
            "completed": "2026-07-20T15:34:31+00:00",
            "elapsed_seconds": 0.016,
            "pdfs_found": 1,
            "files_processed": 6,
            "indexed_or_updated": 1,
            "unchanged": 0,
            "removed_missing": 0,
            "failed": 0,
            "database_documents": 1,
            "database_pages": 1,
            "database_text_chars": 0,
            "original_files_modified": 0,
            "original_files_deleted": 0,
            "ebooks_found": 5,
            "epubs_ready": 2,
            "ebooks_needing_review": 3,
            "ebooks_indexed_or_updated": 5,
            "ebooks_unchanged": 0,
            "ebooks_removed_missing": 0,
            "ebooks_failed": 0,
            "receipt": "/tmp/kayocks_study_v2b_1_http_ifnz6ev9/Reports/20260720T153431_bibliotheca_index_receipt.json"
          }
        },
        {
          "id": "five_ebook_candidates_found",
          "ok": true,
          "detail": {
            "ok": true,
            "cancelled": false,
            "completed": "2026-07-20T15:34:31+00:00",
            "elapsed_seconds": 0.016,
            "pdfs_found": 1,
            "files_processed": 6,
            "indexed_or_updated": 1,
            "unchanged": 0,
            "removed_missing": 0,
            "failed": 0,
            "database_documents": 1,
            "database_pages": 1,
            "database_text_chars": 0,
            "original_files_modified": 0,
            "original_files_deleted": 0,
            "ebooks_found": 5,
            "epubs_ready": 2,
            "ebooks_needing_review": 3,
            "ebooks_indexed_or_updated": 5,
            "ebooks_unchanged": 0,
            "ebooks_removed_missing": 0,
            "ebooks_failed": 0,
            "receipt": "/tmp/kayocks_study_v2b_1_http_ifnz6ev9/Reports/20260720T153431_bibliotheca_index_receipt.json"
          }
        },
        {
          "id": "two_readable_epubs",
          "ok": true,
          "detail": {
            "ok": true,
            "cancelled": false,
            "completed": "2026-07-20T15:34:31+00:00",
            "elapsed_seconds": 0.016,
            "pdfs_found": 1,
            "files_processed": 6,
            "indexed_or_updated": 1,
            "unchanged": 0,
            "removed_missing": 0,
            "failed": 0,
            "database_documents": 1,
            "database_pages": 1,
            "database_text_chars": 0,
            "original_files_modified": 0,
            "original_files_deleted": 0,
            "ebooks_found": 5,
            "epubs_ready": 2,
            "ebooks_needing_review": 3,
            "ebooks_indexed_or_updated": 5,
            "ebooks_unchanged": 0,
            "ebooks_removed_missing": 0,
            "ebooks_failed": 0,
            "receipt": "/tmp/kayocks_study_v2b_1_http_ifnz6ev9/Reports/20260720T153431_bibliotheca_index_receipt.json"
          }
        },
        {
          "id": "three_review_items",
          "ok": true,
          "detail": {
            "ok": true,
            "cancelled": false,
            "completed": "2026-07-20T15:34:31+00:00",
            "elapsed_seconds": 0.016,
            "pdfs_found": 1,
            "files_processed": 6,
            "indexed_or_updated": 1,
            "unchanged": 0,
            "removed_missing": 0,
            "failed": 0,
            "database_documents": 1,
            "database_pages": 1,
            "database_text_chars": 0,
            "original_files_modified": 0,
            "original_files_deleted": 0,
            "ebooks_found": 5,
            "epubs_ready": 2,
            "ebooks_needing_review": 3,
            "ebooks_indexed_or_updated": 5,
            "ebooks_unchanged": 0,
            "ebooks_removed_missing": 0,
            "ebooks_failed": 0,
            "receipt": "/tmp/kayocks_study_v2b_1_http_ifnz6ev9/Reports/20260720T153431_bibliotheca_index_receipt.json"
          }
        },
        {
          "id": "cover_cache_created",
          "ok": true,
          "detail": ""
        },
        {
          "id": "original_ebooks_unchanged",
          "ok": true,
          "detail": ""
        },
        {
          "id": "epub_metadata_parsed",
          "ok": true,
          "detail": [
            {
              "id": 1,
              "rel_path": "Fiction/Star Trek/V2B Test Set/Archive Copy.mobi",
              "title": "Archive Copy",
              "creator": "",
              "language": "",
              "identifier": "",
              "publisher": "",
              "published": "",
              "format": "MOBI",
              "size_bytes": 22,
              "mtime_ns": 1784561671701301798,
              "sha256": "9978848134c10c095b8f3555e8c436751525f117779815124c7a3405c6e47b48",
              "status": "unsupported_format",
              "status_message": ".MOBI is preserved but is not processed in this phase.",
              "encrypted": 0,
              "chapter_count": 0,
              "has_navigation": 0,
              "cover_cache_name": "",
              "cover_media_type": "",
              "indexed_at": "2026-07-20T15:34:31+00:00",
              "shelf": "Fiction",
              "collection": "Star Trek",
              "source_kind": "epub",
              "cover_url": ""
            },
            {
              "id": 2,
              "rel_path": "Fiction/Star Trek/V2B Test Set/Doomsday Continuation.epub",
              "title": "Doomsday Continuation",
              "creator": "Fixture Author",
              "language": "en",
              "identifier": "urn:test:Doomsday Continuation",
              "publisher": "FOXAI Fixture Press",
              "published": "2026-07-20",
              "format": "EPUB",
              "size_bytes": 1885,
              "mtime_ns": 1784561671700353175,
              "sha256": "0a6fb5c328cfcf1e480e4acc4272172525af5443c61baae44e0c93663d27094e",
              "status": "ready",
              "status_message": "EPUB metadata is ready for the Study catalog.",
              "encrypted": 0,
              "chapter_count": 1,
              "has_navigation": 1,
              "cover_cache_name": "0a6fb5c328cfcf1e480e4acc42721725.png",
              "cover_media_type": "image/png",
              "indexed_at": "2026-07-20T15:34:31+00:00",
              "shelf": "Fiction",
              "collection": "Star Trek",
              "source_kind": "epub",
              "cover_url": "/epub/cover?id=2"
            },
            {
              "id": 3,
              "rel_path": "Fiction/Star Trek/V2B Test Set/Malformed Test.epub",
              "title": "Malformed Test",
              "creator": "",
              "language": "",
              "identifier": "",
              "publisher": "",
              "published": "",
              "format": "EPUB",
              "size_bytes": 15,
              "mtime_ns": 1784561671701218315,
              "sha256": "c7c292634233c54a15894f0535fad4993335681718766af71ef1b65b97307122",
              "status": "malformed",
              "status_message": "BadZipFile: File is not a zip file",
              "encrypted": 0,
              "chapter_count": 0,
              "has_navigation": 0,
              "cover_cache_name": "",
              "cover_media_type": "",
              "indexed_at": "2026-07-20T15:34:31+00:00",
              "shelf": "Fiction",
              "collection": "Star Trek",
              "source_kind": "epub",
              "cover_url": ""
            },
            {
              "id": 4,
              "rel_path": "Fiction/Star Trek/V2B Test Set/Protected Test.epub",
              "title": "Protected Test",
              "creator": "",
              "language": "",
              "identifier": "",
              "publisher": "",
              "published": "",
              "format": "EPUB",
              "size_bytes": 2006,
              "mtime_ns": 1784561671701091307,
              "sha256": "70651f28ed5a9e97a8f928949326192cf76b46b9c98874f445bc2410a9e1c93a",
              "status": "encrypted_or_protected",
              "status_message": "An EPUB encryption marker is present; the book was cataloged for review but not processed.",
              "encrypted": 1,
              "chapter_count": 0,
              "has_navigation": 0,
              "cover_cache_name": "",
              "cover_media_type": "",
              "indexed_at": "2026-07-20T15:34:31+00:00",
              "shelf": "Fiction",
              "collection": "Star Trek",
              "source_kind": "epub",
              "cover_url": ""
            },
            {
              "id": 5,
              "rel_path": "Fiction/Star Trek/V2B Test Set/X-Men Crossover.epub",
              "title": "X-Men Crossover",
              "creator": "Fixture Author Two",
              "language": "en",
              "identifier": "urn:test:X-Men Crossover",
              "publisher": "FOXAI Fixture Press",
              "published": "2026-07-20",
              "format": "EPUB",
              "size_bytes": 1648,
              "mtime_ns": 1784561671700712457,
              "sha256": "882a5fe8d8f4fb44e4d485f667ac5e8076f0c24c0739f7cd1efb9fa772402c49",
              "status": "ready",
              "status_message": "EPUB metadata is ready for the Study catalog.",
              "encrypted": 0,
              "chapter_count": 1,
              "has_navigation": 1,
              "cover_cache_name": "",
              "cover_media_type": "",
              "indexed_at": "2026-07-20T15:34:31+00:00",
              "shelf": "Fiction",
              "collection": "Star Trek",
              "source_kind": "epub",
              "cover_url": ""
            }
          ]
        },
        {
          "id": "fiction_and_star_trek_classification",
          "ok": true,
          "detail": [
            {
              "id": 1,
              "rel_path": "Fiction/Star Trek/V2B Test Set/Archive Copy.mobi",
              "title": "Archive Copy",
              "creator": "",
              "language": "",
              "identifier": "",
              "publisher": "",
              "published": "",
              "format": "MOBI",
              "size_bytes": 22,
              "mtime_ns": 1784561671701301798,
              "sha256": "9978848134c10c095b8f3555e8c436751525f117779815124c7a3405c6e47b48",
              "status": "unsupported_format",
              "status_message": ".MOBI is preserved but is not processed in this phase.",
              "encrypted": 0,
              "chapter_count": 0,
              "has_navigation": 0,
              "cover_cache_name": "",
              "cover_media_type": "",
              "indexed_at": "2026-07-20T15:34:31+00:00",
              "shelf": "Fiction",
              "collection": "Star Trek",
              "source_kind": "epub",
              "cover_url": ""
            },
            {
              "id": 2,
              "rel_path": "Fiction/Star Trek/V2B Test Set/Doomsday Continuation.epub",
              "title": "Doomsday Continuation",
              "creator": "Fixture Author",
              "language": "en",
              "identifier": "urn:test:Doomsday Continuation",
              "publisher": "FOXAI Fixture Press",
              "published": "2026-07-20",
              "format": "EPUB",
              "size_bytes": 1885,
              "mtime_ns": 1784561671700353175,
              "sha256": "0a6fb5c328cfcf1e480e4acc4272172525af5443c61baae44e0c93663d27094e",
              "status": "ready",
              "status_message": "EPUB metadata is ready for the Study catalog.",
              "encrypted": 0,
              "chapter_count": 1,
              "has_navigation": 1,
              "cover_cache_name": "0a6fb5c328cfcf1e480e4acc42721725.png",
              "cover_media_type": "image/png",
              "indexed_at": "2026-07-20T15:34:31+00:00",
              "shelf": "Fiction",
              "collection": "Star Trek",
              "source_kind": "epub",
              "cover_url": "/epub/cover?id=2"
            },
            {
              "id": 3,
              "rel_path": "Fiction/Star Trek/V2B Test Set/Malformed Test.epub",
              "title": "Malformed Test",
              "creator": "",
              "language": "",
              "identifier": "",
              "publisher": "",
              "published": "",
              "format": "EPUB",
              "size_bytes": 15,
              "mtime_ns": 1784561671701218315,
              "sha256": "c7c292634233c54a15894f0535fad4993335681718766af71ef1b65b97307122",
              "status": "malformed",
              "status_message": "BadZipFile: File is not a zip file",
              "encrypted": 0,
              "chapter_count": 0,
              "has_navigation": 0,
              "cover_cache_name": "",
              "cover_media_type": "",
              "indexed_at": "2026-07-20T15:34:31+00:00",
              "shelf": "Fiction",
              "collection": "Star Trek",
              "source_kind": "epub",
              "cover_url": ""
            },
            {
              "id": 4,
              "rel_path": "Fiction/Star Trek/V2B Test Set/Protected Test.epub",
              "title": "Protected Test",
              "creator": "",
              "language": "",
              "identifier": "",
              "publisher": "",
              "published": "",
              "format": "EPUB",
              "size_bytes": 2006,
              "mtime_ns": 1784561671701091307,
              "sha256": "70651f28ed5a9e97a8f928949326192cf76b46b9c98874f445bc2410a9e1c93a",
              "status": "encrypted_or_protected",
              "status_message": "An EPUB encryption marker is present; the book was cataloged for review but not processed.",
              "encrypted": 1,
              "chapter_count": 0,
              "has_navigation": 0,
              "cover_cache_name": "",
              "cover_media_type": "",
              "indexed_at": "2026-07-20T15:34:31+00:00",
              "shelf": "Fiction",
              "collection": "Star Trek",
              "source_kind": "epub",
              "cover_url": ""
            },
            {
              "id": 5,
              "rel_path": "Fiction/Star Trek/V2B Test Set/X-Men Crossover.epub",
              "title": "X-Men Crossover",
              "creator": "Fixture Author Two",
              "language": "en",
              "identifier": "urn:test:X-Men Crossover",
              "publisher": "FOXAI Fixture Press",
              "published": "2026-07-20",
              "format": "EPUB",
              "size_bytes": 1648,
              "mtime_ns": 1784561671700712457,
              "sha256": "882a5fe8d8f4fb44e4d485f667ac5e8076f0c24c0739f7cd1efb9fa772402c49",
              "status": "ready",
              "status_message": "EPUB metadata is ready for the Study catalog.",
              "encrypted": 0,
              "chapter_count": 1,
              "has_navigation": 1,
              "cover_cache_name": "",
              "cover_media_type": "",
              "indexed_at": "2026-07-20T15:34:31+00:00",
              "shelf": "Fiction",
              "collection": "Star Trek",
              "source_kind": "epub",
              "cover_url": ""
            }
          ]
        },
        {
          "id": "embedded_cover_available",
          "ok": true,
          "detail": ""
        },
        {
          "id": "placeholder_cover_fallback",
          "ok": true,
          "detail": ""
        },
        {
          "id": "encryption_marker_refused",
          "ok": true,
          "detail": [
            {
              "id": 1,
              "rel_path": "Fiction/Star Trek/V2B Test Set/Archive Copy.mobi",
              "title": "Archive Copy",
              "creator": "",
              "language": "",
              "identifier": "",
              "publisher": "",
              "published": "",
              "format": "MOBI",
              "size_bytes": 22,
              "mtime_ns": 1784561671701301798,
              "sha256": "9978848134c10c095b8f3555e8c436751525f117779815124c7a3405c6e47b48",
              "status": "unsupported_format",
              "status_message": ".MOBI is preserved but is not processed in this phase.",
              "encrypted": 0,
              "chapter_count": 0,
              "has_navigation": 0,
              "cover_cache_name": "",
              "cover_media_type": "",
              "indexed_at": "2026-07-20T15:34:31+00:00",
              "shelf": "Fiction",
              "collection": "Star Trek",
              "source_kind": "epub",
              "cover_url": ""
            },
            {
              "id": 2,
              "rel_path": "Fiction/Star Trek/V2B Test Set/Doomsday Continuation.epub",
              "title": "Doomsday Continuation",
              "creator": "Fixture Author",
              "language": "en",
              "identifier": "urn:test:Doomsday Continuation",
              "publisher": "FOXAI Fixture Press",
              "published": "2026-07-20",
              "format": "EPUB",
              "size_bytes": 1885,
              "mtime_ns": 1784561671700353175,
              "sha256": "0a6fb5c328cfcf1e480e4acc4272172525af5443c61baae44e0c93663d27094e",
              "status": "ready",
              "status_message": "EPUB metadata is ready for the Study catalog.",
              "encrypted": 0,
              "chapter_count": 1,
              "has_navigation": 1,
              "cover_cache_name": "0a6fb5c328cfcf1e480e4acc42721725.png",
              "cover_media_type": "image/png",
              "indexed_at": "2026-07-20T15:34:31+00:00",
              "shelf": "Fiction",
              "collection": "Star Trek",
              "source_kind": "epub",
              "cover_url": "/epub/cover?id=2"
            },
            {
              "id": 3,
              "rel_path": "Fiction/Star Trek/V2B Test Set/Malformed Test.epub",
              "title": "Malformed Test",
              "creator": "",
              "language": "",
              "identifier": "",
              "publisher": "",
              "published": "",
              "format": "EPUB",
              "size_bytes": 15,
              "mtime_ns": 1784561671701218315,
              "sha256": "c7c292634233c54a15894f0535fad4993335681718766af71ef1b65b97307122",
              "status": "malformed",
              "status_message": "BadZipFile: File is not a zip file",
              "encrypted": 0,
              "chapter_count": 0,
              "has_navigation": 0,
              "cover_cache_name": "",
              "cover_media_type": "",
              "indexed_at": "2026-07-20T15:34:31+00:00",
              "shelf": "Fiction",
              "collection": "Star Trek",
              "source_kind": "epub",
              "cover_url": ""
            },
            {
              "id": 4,
              "rel_path": "Fiction/Star Trek/V2B Test Set/Protected Test.epub",
              "title": "Protected Test",
              "creator": "",
              "language": "",
              "identifier": "",
              "publisher": "",
              "published": "",
              "format": "EPUB",
              "size_bytes": 2006,
              "mtime_ns": 1784561671701091307,
              "sha256": "70651f28ed5a9e97a8f928949326192cf76b46b9c98874f445bc2410a9e1c93a",
              "status": "encrypted_or_protected",
              "status_message": "An EPUB encryption marker is present; the book was cataloged for review but not processed.",
              "encrypted": 1,
              "chapter_count": 0,
              "has_navigation": 0,
              "cover_cache_name": "",
              "cover_media_type": "",
              "indexed_at": "2026-07-20T15:34:31+00:00",
              "shelf": "Fiction",
              "collection": "Star Trek",
              "source_kind": "epub",
              "cover_url": ""
            },
            {
              "id": 5,
              "rel_path": "Fiction/Star Trek/V2B Test Set/X-Men Crossover.epub",
              "title": "X-Men Crossover",
              "creator": "Fixture Author Two",
              "language": "en",
              "identifier": "urn:test:X-Men Crossover",
              "publisher": "FOXAI Fixture Press",
              "published": "2026-07-20",
              "format": "EPUB",
              "size_bytes": 1648,
              "mtime_ns": 1784561671700712457,
              "sha256": "882a5fe8d8f4fb44e4d485f667ac5e8076f0c24c0739f7cd1efb9fa772402c49",
              "status": "ready",
              "status_message": "EPUB metadata is ready for the Study catalog.",
              "encrypted": 0,
              "chapter_count": 1,
              "has_navigation": 1,
              "cover_cache_name": "",
              "cover_media_type": "",
              "indexed_at": "2026-07-20T15:34:31+00:00",
              "shelf": "Fiction",
              "collection": "Star Trek",
              "source_kind": "epub",
              "cover_url": ""
            }
          ]
        },
        {
          "id": "malformed_epub_reported",
          "ok": true,
          "detail": [
            {
              "id": 1,
              "rel_path": "Fiction/Star Trek/V2B Test Set/Archive Copy.mobi",
              "title": "Archive Copy",
              "creator": "",
              "language": "",
              "identifier": "",
              "publisher": "",
              "published": "",
              "format": "MOBI",
              "size_bytes": 22,
              "mtime_ns": 1784561671701301798,
              "sha256": "9978848134c10c095b8f3555e8c436751525f117779815124c7a3405c6e47b48",
              "status": "unsupported_format",
              "status_message": ".MOBI is preserved but is not processed in this phase.",
              "encrypted": 0,
              "chapter_count": 0,
              "has_navigation": 0,
              "cover_cache_name": "",
              "cover_media_type": "",
              "indexed_at": "2026-07-20T15:34:31+00:00",
              "shelf": "Fiction",
              "collection": "Star Trek",
              "source_kind": "epub",
              "cover_url": ""
            },
            {
              "id": 2,
              "rel_path": "Fiction/Star Trek/V2B Test Set/Doomsday Continuation.epub",
              "title": "Doomsday Continuation",
              "creator": "Fixture Author",
              "language": "en",
              "identifier": "urn:test:Doomsday Continuation",
              "publisher": "FOXAI Fixture Press",
              "published": "2026-07-20",
              "format": "EPUB",
              "size_bytes": 1885,
              "mtime_ns": 1784561671700353175,
              "sha256": "0a6fb5c328cfcf1e480e4acc4272172525af5443c61baae44e0c93663d27094e",
              "status": "ready",
              "status_message": "EPUB metadata is ready for the Study catalog.",
              "encrypted": 0,
              "chapter_count": 1,
              "has_navigation": 1,
              "cover_cache_name": "0a6fb5c328cfcf1e480e4acc42721725.png",
              "cover_media_type": "image/png",
              "indexed_at": "2026-07-20T15:34:31+00:00",
              "shelf": "Fiction",
              "collection": "Star Trek",
              "source_kind": "epub",
              "cover_url": "/epub/cover?id=2"
            },
            {
              "id": 3,
              "rel_path": "Fiction/Star Trek/V2B Test Set/Malformed Test.epub",
              "title": "Malformed Test",
              "creator": "",
              "language": "",
              "identifier": "",
              "publisher": "",
              "published": "",
              "format": "EPUB",
              "size_bytes": 15,
              "mtime_ns": 1784561671701218315,
              "sha256": "c7c292634233c54a15894f0535fad4993335681718766af71ef1b65b97307122",
              "status": "malformed",
              "status_message": "BadZipFile: File is not a zip file",
              "encrypted": 0,
              "chapter_count": 0,
              "has_navigation": 0,
              "cover_cache_name": "",
              "cover_media_type": "",
              "indexed_at": "2026-07-20T15:34:31+00:00",
              "shelf": "Fiction",
              "collection": "Star Trek",
              "source_kind": "epub",
              "cover_url": ""
            },
            {
              "id": 4,
              "rel_path": "Fiction/Star Trek/V2B Test Set/Protected Test.epub",
              "title": "Protected Test",
              "creator": "",
              "language": "",
              "identifier": "",
              "publisher": "",
              "published": "",
              "format": "EPUB",
              "size_bytes": 2006,
              "mtime_ns": 1784561671701091307,
              "sha256": "70651f28ed5a9e97a8f928949326192cf76b46b9c98874f445bc2410a9e1c93a",
              "status": "encrypted_or_protected",
              "status_message": "An EPUB encryption marker is present; the book was cataloged for review but not processed.",
              "encrypted": 1,
              "chapter_count": 0,
              "has_navigation": 0,
              "cover_cache_name": "",
              "cover_media_type": "",
              "indexed_at": "2026-07-20T15:34:31+00:00",
              "shelf": "Fiction",
              "collection": "Star Trek",
              "source_kind": "epub",
              "cover_url": ""
            },
            {
              "id": 5,
              "rel_path": "Fiction/Star Trek/V2B Test Set/X-Men Crossover.epub",
              "title": "X-Men Crossover",
              "creator": "Fixture Author Two",
              "language": "en",
              "identifier": "urn:test:X-Men Crossover",
              "publisher": "FOXAI Fixture Press",
              "published": "2026-07-20",
              "format": "EPUB",
              "size_bytes": 1648,
              "mtime_ns": 1784561671700712457,
              "sha256": "882a5fe8d8f4fb44e4d485f667ac5e8076f0c24c0739f7cd1efb9fa772402c49",
              "status": "ready",
              "status_message": "EPUB metadata is ready for the Study catalog.",
              "encrypted": 0,
              "chapter_count": 1,
              "has_navigation": 1,
              "cover_cache_name": "",
              "cover_media_type": "",
              "indexed_at": "2026-07-20T15:34:31+00:00",
              "shelf": "Fiction",
              "collection": "Star Trek",
              "source_kind": "epub",
              "cover_url": ""
            }
          ]
        },
        {
          "id": "mobi_reported_unsupported",
          "ok": true,
          "detail": [
            {
              "id": 1,
              "rel_path": "Fiction/Star Trek/V2B Test Set/Archive Copy.mobi",
              "title": "Archive Copy",
              "creator": "",
              "language": "",
              "identifier": "",
              "publisher": "",
              "published": "",
              "format": "MOBI",
              "size_bytes": 22,
              "mtime_ns": 1784561671701301798,
              "sha256": "9978848134c10c095b8f3555e8c436751525f117779815124c7a3405c6e47b48",
              "status": "unsupported_format",
              "status_message": ".MOBI is preserved but is not processed in this phase.",
              "encrypted": 0,
              "chapter_count": 0,
              "has_navigation": 0,
              "cover_cache_name": "",
              "cover_media_type": "",
              "indexed_at": "2026-07-20T15:34:31+00:00",
              "shelf": "Fiction",
              "collection": "Star Trek",
              "source_kind": "epub",
              "cover_url": ""
            },
            {
              "id": 2,
              "rel_path": "Fiction/Star Trek/V2B Test Set/Doomsday Continuation.epub",
              "title": "Doomsday Continuation",
              "creator": "Fixture Author",
              "language": "en",
              "identifier": "urn:test:Doomsday Continuation",
              "publisher": "FOXAI Fixture Press",
              "published": "2026-07-20",
              "format": "EPUB",
              "size_bytes": 1885,
              "mtime_ns": 1784561671700353175,
              "sha256": "0a6fb5c328cfcf1e480e4acc4272172525af5443c61baae44e0c93663d27094e",
              "status": "ready",
              "status_message": "EPUB metadata is ready for the Study catalog.",
              "encrypted": 0,
              "chapter_count": 1,
              "has_navigation": 1,
              "cover_cache_name": "0a6fb5c328cfcf1e480e4acc42721725.png",
              "cover_media_type": "image/png",
              "indexed_at": "2026-07-20T15:34:31+00:00",
              "shelf": "Fiction",
              "collection": "Star Trek",
              "source_kind": "epub",
              "cover_url": "/epub/cover?id=2"
            },
            {
              "id": 3,
              "rel_path": "Fiction/Star Trek/V2B Test Set/Malformed Test.epub",
              "title": "Malformed Test",
              "creator": "",
              "language": "",
              "identifier": "",
              "publisher": "",
              "published": "",
              "format": "EPUB",
              "size_bytes": 15,
              "mtime_ns": 1784561671701218315,
              "sha256": "c7c292634233c54a15894f0535fad4993335681718766af71ef1b65b97307122",
              "status": "malformed",
              "status_message": "BadZipFile: File is not a zip file",
              "encrypted": 0,
              "chapter_count": 0,
              "has_navigation": 0,
              "cover_cache_name": "",
              "cover_media_type": "",
              "indexed_at": "2026-07-20T15:34:31+00:00",
              "shelf": "Fiction",
              "collection": "Star Trek",
              "source_kind": "epub",
              "cover_url": ""
            },
            {
              "id": 4,
              "rel_path": "Fiction/Star Trek/V2B Test Set/Protected Test.epub",
              "title": "Protected Test",
              "creator": "",
              "language": "",
              "identifier": "",
              "publisher": "",
              "published": "",
              "format": "EPUB",
              "size_bytes": 2006,
              "mtime_ns": 1784561671701091307,
              "sha256": "70651f28ed5a9e97a8f928949326192cf76b46b9c98874f445bc2410a9e1c93a",
              "status": "encrypted_or_protected",
              "status_message": "An EPUB encryption marker is present; the book was cataloged for review but not processed.",
              "encrypted": 1,
              "chapter_count": 0,
              "has_navigation": 0,
              "cover_cache_name": "",
              "cover_media_type": "",
              "indexed_at": "2026-07-20T15:34:31+00:00",
              "shelf": "Fiction",
              "collection": "Star Trek",
              "source_kind": "epub",
              "cover_url": ""
            },
            {
              "id": 5,
              "rel_path": "Fiction/Star Trek/V2B Test Set/X-Men Crossover.epub",
              "title": "X-Men Crossover",
              "creator": "Fixture Author Two",
              "language": "en",
              "identifier": "urn:test:X-Men Crossover",
              "publisher": "FOXAI Fixture Press",
              "published": "2026-07-20",
              "format": "EPUB",
              "size_bytes": 1648,
              "mtime_ns": 1784561671700712457,
              "sha256": "882a5fe8d8f4fb44e4d485f667ac5e8076f0c24c0739f7cd1efb9fa772402c49",
              "status": "ready",
              "status_message": "EPUB metadata is ready for the Study catalog.",
              "encrypted": 0,
              "chapter_count": 1,
              "has_navigation": 1,
              "cover_cache_name": "",
              "cover_media_type": "",
              "indexed_at": "2026-07-20T15:34:31+00:00",
              "shelf": "Fiction",
              "collection": "Star Trek",
              "source_kind": "epub",
              "cover_url": ""
            }
          ]
        },
        {
          "id": "bibliotheca_schema_not_extended_with_ebooks",
          "ok": true,
          "detail": [
            "documents",
            "metadata",
            "pages",
            "pages_fts",
            "pages_fts_config",
            "pages_fts_content",
            "pages_fts_data",
            "pages_fts_docsize",
            "pages_fts_idx",
            "research_captures",
            "research_segments"
          ]
        },
        {
          "id": "sidecar_database_exists",
          "ok": true,
          "detail": ""
        },
        {
          "id": "duplicate_rescan_is_incremental",
          "ok": true,
          "detail": {
            "ok": true,
            "cancelled": false,
            "completed": "2026-07-20T15:34:31+00:00",
            "elapsed_seconds": 0.004,
            "pdfs_found": 1,
            "files_processed": 6,
            "indexed_or_updated": 0,
            "unchanged": 1,
            "removed_missing": 0,
            "failed": 0,
            "database_documents": 1,
            "database_pages": 1,
            "database_text_chars": 0,
            "original_files_modified": 0,
            "original_files_deleted": 0,
            "ebooks_found": 5,
            "epubs_ready": 2,
            "ebooks_needing_review": 3,
            "ebooks_indexed_or_updated": 0,
            "ebooks_unchanged": 5,
            "ebooks_removed_missing": 0,
            "ebooks_failed": 0,
            "receipt": "/tmp/kayocks_study_v2b_1_http_ifnz6ev9/Reports/20260720T153431_bibliotheca_index_receipt.json"
          }
        },
        {
          "id": "duplicate_rescan_keeps_single_cover",
          "ok": true,
          "detail": ""
        },
        {
          "id": "status_http_reports_epubs",
          "ok": true,
          "detail": {
            "ok": true,
            "app": "Kayock's Study",
            "version": "2B.1",
            "collection": "The Bibliotheca",
            "motto": "Read. Research. Preserve. Discover.",
            "root": "/tmp/kayocks_study_v2b_1_http_ifnz6ev9",
            "library": "/tmp/kayocks_study_v2b_1_http_ifnz6ev9/Library",
            "database": "/tmp/kayocks_study_v2b_1_http_ifnz6ev9/Data/bibliotheca.sqlite3",
            "summary": {
              "documents": 1,
              "pages": 1,
              "text_chars": 0,
              "searchable": 0,
              "low_text": 1,
              "ocr_copies": 0,
              "shelves": 1,
              "fts5": true,
              "research_saved": 0,
              "research_segments": 0,
              "research_revisions": 0,
              "duplicate_groups": 0
            },
            "ebook_summary": {
              "ebooks": 5,
              "ready": 2,
              "needs_review": 3,
              "with_covers": 1,
              "collections": 1
            },
            "state": {
              "indexing": false,
              "paused": false,
              "cancel_requested": false,
              "started_at": "2026-07-20T15:34:31+00:00",
              "current_file": "",
              "scanned": 6,
              "total": 6,
              "elapsed_seconds": 0.0,
              "files_per_second": 1500.0,
              "last_result": {
                "ok": true,
                "cancelled": false,
                "completed": "2026-07-20T15:34:31+00:00",
                "elapsed_seconds": 0.004,
                "pdfs_found": 1,
                "files_processed": 6,
                "indexed_or_updated": 0,
                "unchanged": 1,
                "removed_missing": 0,
                "failed": 0,
                "database_documents": 1,
                "database_pages": 1,
                "database_text_chars": 0,
                "original_files_modified": 0,
                "original_files_deleted": 0,
                "ebooks_found": 5,
                "epubs_ready": 2,
                "ebooks_needing_review": 3,
                "ebooks_indexed_or_updated": 0,
                "ebooks_unchanged": 5,
                "ebooks_removed_missing": 0,
                "ebooks_failed": 0,
                "receipt": "/tmp/kayocks_study_v2b_1_http_ifnz6ev9/Reports/20260720T153431_bibliotheca_index_receipt.json"
              },
              "last_error": ""
            },
            "model_online": false,
            "model_name": "",
            "model_message": "Health check unavailable: HTTPError.",
            "network_scope": "localhost_only",
            "research_session": {
              "enabled": false,
              "status": "OFFLINE",
              "last_error": "",
              "preview_count": 0,
              "policy": {
                "session_only": true,
                "network_off_by_default": true,
                "automatic_search": false,
                "background_crawling": false,
                "telemetry": false,
                "prefetch": false,
                "cookies": false,
                "javascript": false,
                "forms": false
              }
            },
            "original_files_modified": 0
          }
        },
        {
          "id": "ebooks_http_200",
          "ok": true,
          "detail": {
            "ok": true,
            "summary": {
              "ebooks": 5,
              "ready": 2,
              "needs_review": 3,
              "with_covers": 1,
              "collections": 1
            },
            "ebooks": [
              {
                "id": 1,
                "rel_path": "Fiction/Star Trek/V2B Test Set/Archive Copy.mobi",
                "title": "Archive Copy",
                "creator": "",
                "language": "",
                "identifier": "",
                "publisher": "",
                "published": "",
                "format": "MOBI",
                "size_bytes": 22,
                "mtime_ns": 1784561671701301798,
                "sha256": "9978848134c10c095b8f3555e8c436751525f117779815124c7a3405c6e47b48",
                "status": "unsupported_format",
                "status_message": ".MOBI is preserved but is not processed in this phase.",
                "encrypted": 0,
                "chapter_count": 0,
                "has_navigation": 0,
                "cover_cache_name": "",
                "cover_media_type": "",
                "indexed_at": "2026-07-20T15:34:31+00:00",
                "shelf": "Fiction",
                "collection": "Star Trek",
                "source_kind": "epub",
                "cover_url": ""
              },
              {
                "id": 2,
                "rel_path": "Fiction/Star Trek/V2B Test Set/Doomsday Continuation.epub",
                "title": "Doomsday Continuation",
                "creator": "Fixture Author",
                "language": "en",
                "identifier": "urn:test:Doomsday Continuation",
                "publisher": "FOXAI Fixture Press",
                "published": "2026-07-20",
                "format": "EPUB",
                "size_bytes": 1885,
                "mtime_ns": 1784561671700353175,
                "sha256": "0a6fb5c328cfcf1e480e4acc4272172525af5443c61baae44e0c93663d27094e",
                "status": "ready",
                "status_message": "EPUB metadata is ready for the Study catalog.",
                "encrypted": 0,
                "chapter_count": 1,
                "has_navigation": 1,
                "cover_cache_name": "0a6fb5c328cfcf1e480e4acc42721725.png",
                "cover_media_type": "image/png",
                "indexed_at": "2026-07-20T15:34:31+00:00",
                "shelf": "Fiction",
                "collection": "Star Trek",
                "source_kind": "epub",
                "cover_url": "/epub/cover?id=2"
              },
              {
                "id": 3,
                "rel_path": "Fiction/Star Trek/V2B Test Set/Malformed Test.epub",
                "title": "Malformed Test",
                "creator": "",
                "language": "",
                "identifier": "",
                "publisher": "",
                "published": "",
                "format": "EPUB",
                "size_bytes": 15,
                "mtime_ns": 1784561671701218315,
                "sha256": "c7c292634233c54a15894f0535fad4993335681718766af71ef1b65b97307122",
                "status": "malformed",
                "status_message": "BadZipFile: File is not a zip file",
                "encrypted": 0,
                "chapter_count": 0,
                "has_navigation": 0,
                "cover_cache_name": "",
                "cover_media_type": "",
                "indexed_at": "2026-07-20T15:34:31+00:00",
                "shelf": "Fiction",
                "collection": "Star Trek",
                "source_kind": "epub",
                "cover_url": ""
              },
              {
                "id": 4,
                "rel_path": "Fiction/Star Trek/V2B Test Set/Protected Test.epub",
                "title": "Protected Test",
                "creator": "",
                "language": "",
                "identifier": "",
                "publisher": "",
                "published": "",
                "format": "EPUB",
                "size_bytes": 2006,
                "mtime_ns": 1784561671701091307,
                "sha256": "70651f28ed5a9e97a8f928949326192cf76b46b9c98874f445bc2410a9e1c93a",
                "status": "encrypted_or_protected",
                "status_message": "An EPUB encryption marker is present; the book was cataloged for review but not processed.",
                "encrypted": 1,
                "chapter_count": 0,
                "has_navigation": 0,
                "cover_cache_name": "",
                "cover_media_type": "",
                "indexed_at": "2026-07-20T15:34:31+00:00",
                "shelf": "Fiction",
                "collection": "Star Trek",
                "source_kind": "epub",
                "cover_url": ""
              },
              {
                "id": 5,
                "rel_path": "Fiction/Star Trek/V2B Test Set/X-Men Crossover.epub",
                "title": "X-Men Crossover",
                "creator": "Fixture Author Two",
                "language": "en",
                "identifier": "urn:test:X-Men Crossover",
                "publisher": "FOXAI Fixture Press",
                "published": "2026-07-20",
                "format": "EPUB",
                "size_bytes": 1648,
                "mtime_ns": 1784561671700712457,
                "sha256": "882a5fe8d8f4fb44e4d485f667ac5e8076f0c24c0739f7cd1efb9fa772402c49",
                "status": "ready",
                "status_message": "EPUB metadata is ready for the Study catalog.",
                "encrypted": 0,
                "chapter_count": 1,
                "has_navigation": 1,
                "cover_cache_name": "",
                "cover_media_type": "",
                "indexed_at": "2026-07-20T15:34:31+00:00",
                "shelf": "Fiction",
                "collection": "Star Trek",
                "source_kind": "epub",
                "cover_url": ""
              }
            ]
          }
        },
        {
          "id": "star_trek_http_visibility",
          "ok": true,
          "detail": [
            {
              "id": 2,
              "rel_path": "Fiction/Star Trek/V2B Test Set/Doomsday Continuation.epub",
              "title": "Doomsday Continuation",
              "creator": "Fixture Author",
              "language": "en",
              "identifier": "urn:test:Doomsday Continuation",
              "publisher": "FOXAI Fixture Press",
              "published": "2026-07-20",
              "format": "EPUB",
              "size_bytes": 1885,
              "mtime_ns": 1784561671700353175,
              "sha256": "0a6fb5c328cfcf1e480e4acc4272172525af5443c61baae44e0c93663d27094e",
              "status": "ready",
              "status_message": "EPUB metadata is ready for the Study catalog.",
              "encrypted": 0,
              "chapter_count": 1,
              "has_navigation": 1,
              "cover_cache_name": "0a6fb5c328cfcf1e480e4acc42721725.png",
              "cover_media_type": "image/png",
              "indexed_at": "2026-07-20T15:34:31+00:00",
              "shelf": "Fiction",
              "collection": "Star Trek",
              "source_kind": "epub",
              "cover_url": "/epub/cover?id=2"
            },
            {
              "id": 5,
              "rel_path": "Fiction/Star Trek/V2B Test Set/X-Men Crossover.epub",
              "title": "X-Men Crossover",
              "creator": "Fixture Author Two",
              "language": "en",
              "identifier": "urn:test:X-Men Crossover",
              "publisher": "FOXAI Fixture Press",
              "published": "2026-07-20",
              "format": "EPUB",
              "size_bytes": 1648,
              "mtime_ns": 1784561671700712457,
              "sha256": "882a5fe8d8f4fb44e4d485f667ac5e8076f0c24c0739f7cd1efb9fa772402c49",
              "status": "ready",
              "status_message": "EPUB metadata is ready for the Study catalog.",
              "encrypted": 0,
              "chapter_count": 1,
              "has_navigation": 1,
              "cover_cache_name": "",
              "cover_media_type": "",
              "indexed_at": "2026-07-20T15:34:31+00:00",
              "shelf": "Fiction",
              "collection": "Star Trek",
              "source_kind": "epub",
              "cover_url": ""
            }
          ]
        },
        {
          "id": "cover_http_200",
          "ok": true,
          "detail": ""
        },
        {
          "id": "existing_pdf_documents_api_unchanged",
          "ok": true,
          "detail": {
            "ok": true,
            "documents": [
              {
                "id": 1,
                "rel_path": "Manuals/Fixture Manual.pdf",
                "title": "Fixture Manual",
                "size_bytes": 431,
                "page_count": 1,
                "indexed_pages": 1,
                "text_chars": 0,
                "low_text_pages": 1,
                "extraction_errors": 0,
                "text_status": "image_only_or_low_text",
                "is_ocr_copy": 0,
                "related_stem": "fixture manual",
                "indexed_at": "2026-07-20T15:34:31+00:00",
                "sha256": "3de2b3788e3232e4fcc07525e218a18d7d81a158d452654317a044163dfb710b",
                "shelf": "Manuals",
                "is_duplicate_candidate": false,
                "has_related_copy": false
              }
            ]
          }
        },
        {
          "id": "existing_pdf_search_api_returns_json",
          "ok": true,
          "detail": {
            "ok": true,
            "query": "nothing",
            "results": []
          }
        },
        {
          "id": "removed_epub_catalog_cleanup",
          "ok": true,
          "detail": {
            "ok": true,
            "cancelled": false,
            "completed": "2026-07-20T15:34:31+00:00",
            "elapsed_seconds": 0.005,
            "pdfs_found": 1,
            "files_processed": 5,
            "indexed_or_updated": 0,
            "unchanged": 1,
            "removed_missing": 0,
            "failed": 0,
            "database_documents": 1,
            "database_pages": 1,
            "database_text_chars": 0,
            "original_files_modified": 0,
            "original_files_deleted": 0,
            "ebooks_found": 4,
            "epubs_ready": 1,
            "ebooks_needing_review": 3,
            "ebooks_indexed_or_updated": 0,
            "ebooks_unchanged": 4,
            "ebooks_removed_missing": 1,
            "ebooks_failed": 0,
            "receipt": "/tmp/kayocks_study_v2b_1_http_ifnz6ev9/Reports/20260720T153431_bibliotheca_index_receipt.json"
          }
        },
        {
          "id": "removed_epub_absent",
          "ok": true,
          "detail": ""
        },
        {
          "id": "safe_member_rejects_traversal",
          "ok": true,
          "detail": ""
        }
      ],
      "safety": {
        "external_network_used": false,
        "loopback_http_only": true,
        "original_ebooks_modified": 0,
        "bibliotheca_schema_changed": false,
        "external_library_scanned": false
      }
    },
    "v1_2_and_v1_2_2_source_compatibility": "passed separately; final exact validations run against the live known-good FOXAI WebUI hash during Engineering Workshop apply"
  },
  "safety": {
    "external_network_used": false,
    "loopback_http_only": true,
    "library_content_changed": 0,
    "original_epubs_changed": 0,
    "original_pdfs_changed": 0,
    "bibliotheca_schema_changed": 0,
    "external_drive_scanned": 0,
    "writer_files_changed": 0,
    "poetry_files_changed": 0,
    "repair_bay_files_changed": 0,
    "models_or_runtimes_changed": 0,
    "moves": 0,
    "renames": 0,
    "original_deletions": 0,
    "installations": 0,
    "downloads": 0
  }
}
